aquapointer/__init__.py
aquapointer/slicing.py
aquapointer-0.0.2.dist-info/LICENSE
aquapointer-0.0.2.dist-info/METADATA
aquapointer-0.0.2.dist-info/WHEEL
aquapointer-0.0.2.dist-info/top_level.txt
aquapointer-0.0.2.dist-info/RECORD
