Metadata-Version: 2.1
Name: aquapointer
Version: 0.0.2
Summary: aquapointer
Author: Unitary Fund
Classifier: Development Status :: 2 - Pre-Alpha
Classifier: License :: OSI Approved :: GNU General Public License v3 (GPLv3)
Classifier: Programming Language :: Python :: 3
Classifier: Programming Language :: Python :: 3.11
License-File: LICENSE
